cute_cats_terminal/__init__.py
cute_cats_terminal/_cats.py
cute_cats_terminal/_emojis.py
cute_cats_terminal/_print.py
cute_cats_terminal-0.3.1.dist-info/METADATA
cute_cats_terminal-0.3.1.dist-info/WHEEL
cute_cats_terminal-0.3.1.dist-info/RECORD
