Metadata-Version: 2.4
Name: cute-cats-terminal
Version: 0.3.1
Summary: A package to print cute cats to terminal
Requires-Python: <4,>=3.9
Requires-Dist: termcolor>=3.1.0
